zksk/__init__.py
zksk/base.py
zksk/composition.py
zksk/consts.py
zksk/exceptions.py
zksk/expr.py
zksk/extended.py
zksk/pairings.py
zksk/primitives/__init__.py
zksk/primitives/bbsplus.py
zksk/primitives/dl_notequal.py
zksk/primitives/dlrep.py
zksk/primitives/rangeproof.py
zksk/utils/__init__.py
zksk/utils/debug.py
zksk/utils/groups.py
zksk/utils/misc.py
zksk_fork-0.0.31.dist-info/LICENSE
zksk_fork-0.0.31.dist-info/METADATA
zksk_fork-0.0.31.dist-info/WHEEL
zksk_fork-0.0.31.dist-info/top_level.txt
zksk_fork-0.0.31.dist-info/RECORD
