Metadata-Version: 2.1
Name: zksk-fork
Version: 0.0.31
Summary: Zero-Knowledge Swiss Knife: Python library for prototyping composable zero-knowledge proofs.
Home-page: https://zksk.readthedocs.io
Author: Wouter Lueks, Bogdan Kulynych, Jules Fasquelle, Simon Le Bail-Collet
Author-email: wouter.lueks@epfl.ch
License: MIT
Classifier: Development Status :: 3 - Alpha
Classifier: Intended Audience :: Developers
Classifier: Natural Language :: English
Classifier: Operating System :: OS Independent
Classifier: Programming Language :: Python
Classifier: Programming Language :: Python :: 3
Classifier: Programming Language :: Python :: 3.6
Classifier: Programming Language :: Python :: Implementation :: CPython
Classifier: Topic :: Software Development :: Libraries :: Python Modules
Classifier: Topic :: Security :: Cryptography
Classifier: License :: OSI Approved :: MIT License
License-File: LICENSE
Requires-Dist: petlib-fork
Requires-Dist: bplib-fork
Provides-Extra: dev
Requires-Dist: pytest ; extra == 'dev'
Requires-Dist: sphinx ; extra == 'dev'
Requires-Dist: sphinx-rtd-theme ; extra == 'dev'
Requires-Dist: m2r ; extra == 'dev'
Requires-Dist: black ; extra == 'dev'
Requires-Dist: pre-commit ; extra == 'dev'
Requires-Dist: pytest-cov ; extra == 'dev'
Provides-Extra: doc
Requires-Dist: sphinx ; extra == 'doc'
Requires-Dist: sphinx-rtd-theme ; extra == 'doc'
Requires-Dist: m2r ; extra == 'doc'
Provides-Extra: test
Requires-Dist: pytest ; extra == 'test'
